pdtools2/__init__.py
pdtools2/pd_viz.py
pdtools2/reduce_memory/__init__.py
pdtools2/reduce_memory/mem_reduce.py
pdtools2-0.1.0.dist-info/LICENSE
pdtools2-0.1.0.dist-info/METADATA
pdtools2-0.1.0.dist-info/WHEEL
pdtools2-0.1.0.dist-info/top_level.txt
pdtools2-0.1.0.dist-info/RECORD
