Metadata-Version: 2.1
Name: pdtools2
Version: 0.1.0
Summary: A package that helps reduce memory usage when working with pandas
Home-page: UNKNOWN
Author: Masum Rumi
License: UNKNOWN
Platform: UNKNOWN
Requires-Python: >=3.8
Requires-Dist: pandas (>=1.0.0)
Requires-Dist: numpy (>=1.18.0)
